client.py
config.example.py
example.py
main.py
midjounery.py
midjounery_manager.py
test.py
midjounery_python_sdk-0.1.0.dist-info/LICENSE
midjounery_python_sdk-0.1.0.dist-info/METADATA
midjounery_python_sdk-0.1.0.dist-info/WHEEL
midjounery_python_sdk-0.1.0.dist-info/RECORD
