Metadata-Version: 2.1
Name: midjounery-python-sdk
Version: 0.1.0
Summary: Python client for the unofficial MidJourney API.
Home-page: https://github.com/ezioruan/midjourney-python-api
Author: ezioruan
Author-email: ezioruan@gmail.com
Requires-Python: >=3.10,<4.0
Classifier: Programming Language :: Python :: 3
Classifier: Programming Language :: Python :: 3.10
Classifier: Programming Language :: Python :: 3.11
Project-URL: Repository, https://github.com/ezioruan/midjourney-python-api
